zhenxun_bot/basic_plugins/__init__.py
zhenxun_bot/basic_plugins/admin_bot_manage/__init__.py
zhenxun_bot/basic_plugins/admin_bot_manage/_data_source.py
zhenxun_bot/basic_plugins/admin_bot_manage/admin_config.py
zhenxun_bot/basic_plugins/admin_bot_manage/custom_welcome_message.py
zhenxun_bot/basic_plugins/admin_bot_manage/rule.py
zhenxun_bot/basic_plugins/admin_bot_manage/switch_rule.py
zhenxun_bot/basic_plugins/admin_bot_manage/timing_task.py
zhenxun_bot/basic_plugins/admin_bot_manage/update_group_member_info.py
zhenxun_bot/basic_plugins/admin_help/__init__.py
zhenxun_bot/basic_plugins/admin_help/data_source.py
zhenxun_bot/basic_plugins/apscheduler/__init__.py
zhenxun_bot/basic_plugins/ban/__init__.py
zhenxun_bot/basic_plugins/ban/data_source.py
zhenxun_bot/basic_plugins/broadcast/__init__.py
zhenxun_bot/basic_plugins/group_handle/__init__.py
zhenxun_bot/basic_plugins/help/__init__.py
zhenxun_bot/basic_plugins/help/data_source.py
zhenxun_bot/basic_plugins/hooks/__init__.py
zhenxun_bot/basic_plugins/hooks/_utils.py
zhenxun_bot/basic_plugins/hooks/auth_hook.py
zhenxun_bot/basic_plugins/hooks/ban_hook.py
zhenxun_bot/basic_plugins/hooks/chkdsk_hook.py
zhenxun_bot/basic_plugins/hooks/other_hook.py
zhenxun_bot/basic_plugins/hooks/task_hook.py
zhenxun_bot/basic_plugins/hooks/withdraw_message_hook.py
zhenxun_bot/basic_plugins/init_plugin_config/__init__.py
zhenxun_bot/basic_plugins/init_plugin_config/check_plugin_status.py
zhenxun_bot/basic_plugins/init_plugin_config/init.py
zhenxun_bot/basic_plugins/init_plugin_config/init_group_manager.py
zhenxun_bot/basic_plugins/init_plugin_config/init_none_plugin_count_manager.py
zhenxun_bot/basic_plugins/init_plugin_config/init_plugins_config.py
zhenxun_bot/basic_plugins/init_plugin_config/init_plugins_data.py
zhenxun_bot/basic_plugins/init_plugin_config/init_plugins_limit.py
zhenxun_bot/basic_plugins/init_plugin_config/init_plugins_resources.py
zhenxun_bot/basic_plugins/init_plugin_config/init_plugins_settings.py
zhenxun_bot-0.1.4.3.dist-info/LICENSE
zhenxun_bot-0.1.4.3.dist-info/WHEEL
zhenxun_bot-0.1.4.3.dist-info/METADATA
zhenxun_bot-0.1.4.3.dist-info/RECORD
