Metadata-Version: 2.1
Name: zhenxun-bot
Version: 0.1.4.3
Summary: 基于 Nonebot2 和 go-cqhttp 开发，以 postgresql 作为数据库，非常可爱的绪山真寻bot
License: AGPL
Author: HibiKier
Author-email: 775757368@qq.com
Requires-Python: >=3.8,<4.0
Classifier: License :: Other/Proprietary License
Classifier: Programming Language :: Python :: 3
Classifier: Programming Language :: Python :: 3.10
Classifier: Programming Language :: Python :: 3.8
Classifier: Programming Language :: Python :: 3.9
Requires-Dist: ImageHash (>=4.2.1,<5.0.0)
Requires-Dist: Pillow (>=9.0.1,<10.0.0)
Requires-Dist: PyYAML (==5.4.1)
Requires-Dist: aiofiles (>=0.8.0,<0.9.0)
Requires-Dist: aiohttp (==3.7.4.post0)
Requires-Dist: beautifulsoup4 (==4.9.3)
Requires-Dist: bilibili-api (>=9.1.0,<10.0.0)
Requires-Dist: black (>=22.1.0,<23.0.0)
Requires-Dist: cn2an (>=0.5.16,<0.6.0)
Requires-Dist: dateparser (>=1.1.0,<2.0.0)
Requires-Dist: feedparser (>=6.0.8,<7.0.0)
Requires-Dist: gino (>=1.0.1,<2.0.0)
Requires-Dist: httpx (>=0.22.0,<0.23.0)
Requires-Dist: jieba (>=0.42.1,<0.43.0)
Requires-Dist: lxml (==4.6.5)
Requires-Dist: matplotlib (>=3.5.1,<4.0.0)
Requires-Dist: nonebot-adapter-onebot (>=2.0.0-beta.1,<3.0.0)
Requires-Dist: nonebot-plugin-apscheduler (>=0.1.2,<0.2.0)
Requires-Dist: nonebot2 (>=2.0.0-beta.2,<3.0.0)
Requires-Dist: opencv-python (>=4.5.5,<5.0.0)
Requires-Dist: playwright (>=1.18.2,<2.0.0)
Requires-Dist: psutil (>=5.9.0,<6.0.0)
Requires-Dist: pypinyin (>=0.46.0,<0.47.0)
Requires-Dist: retrying (>=1.3.3,<2.0.0)
Requires-Dist: ruamel.yaml (>=0.17.21,<0.18.0)
Requires-Dist: ujson (>=5.1.0,<6.0.0)
